pyzotero/__init__.py
pyzotero/cli.py
pyzotero/filetransport.py
pyzotero/zotero.py
pyzotero/zotero_errors.py
pyzotero-1.7.5.dist-info/WHEEL
pyzotero-1.7.5.dist-info/entry_points.txt
pyzotero-1.7.5.dist-info/METADATA
pyzotero-1.7.5.dist-info/RECORD
