Metadata-Version: 2.3
Name: pyzotero
Version: 1.7.5
Summary: Python wrapper for the Zotero API
Keywords: Zotero,DH
Author: Stephan Hügel
Author-email: Stephan Hügel <urschrei@gmail.com>
License: # Blue Oak Model License
Classifier: Programming Language :: Python
Classifier: Programming Language :: Python :: 3.9
Classifier: Programming Language :: Python :: 3.10
Classifier: Programming Language :: Python :: 3.11
Classifier: Programming Language :: Python :: 3.12
Classifier: Programming Language :: Python :: 3.13
Classifier: Development Status :: 5 - Production/Stable
Classifier: Intended Audience :: Developers
Classifier: Intended Audience :: Science/Research
Classifier: Intended Audience :: Education
Classifier: License :: OSI Approved :: Blue Oak Model License (BlueOak-1.0.0)
Classifier: Operating System :: OS Independent
Classifier: Topic :: Software Development :: Libraries :: Python Modules
Requires-Dist: feedparser>=6.0.12
Requires-Dist: bibtexparser>=1.4.3,<2.0.0
Requires-Dist: httpx>=0.28.1
Requires-Dist: whenever>=0.8.8
Requires-Dist: click>=8.0.0 ; extra == 'cli'
Requires-Python: >=3.9
Project-URL: Repository, https://github.com/urschrei/pyzotero
Project-URL: Tracker, https://github.com/urschrei/pyzotero/issues
Project-URL: documentation, https://pyzotero.readthedocs.org
Provides-Extra: cli
